{"nodes": [{"data": {"id": "mat:Conformal coatings", "label": "Conformal coatings", "layer": "material", "dependency_type": "process_consumable"}}, {"data": {"id": "domain:biotechnology", "label": "Biotechnology", "layer": "domain"}}, {"data": {"id": "subdomain:biotechnology:Bioprocessing Equipment", "label": "Bioprocessing Equipment", "layer": "subdomain"}}, {"data": {"id": "tech:Industrial Freeze Dryer (Lyophilizer)", "label": "Industrial Freeze Dryer (Lyophilizer)", "layer": "technology", "num_components": 1, "dependency_types": ["process_consumable"]}}, {"data": {"id": "domain:pharmaceuticals", "label": "Pharmaceuticals", "layer": "domain"}}, {"data": {"id": "subdomain:pharmaceuticals:Clinical Trial Supply", "label": "Clinical Trial Supply", "layer": "subdomain"}}, {"data": {"id": "tech:Comparator Sourcing and Over-Encapsulation Machine", "label": "Comparator Sourcing and Over-Encapsulation Machine", "layer": "technology", "num_components": 1, "dependency_types": ["process_consumable"]}}], "edges": [{"data": {"id": "mat:Conformal coatings->domain:biotechnology", "source": "mat:Conformal coatings", "target": "domain:biotechnology", "edge_type": "USED_IN_DOMAIN"}}, {"data": {"id": "domain:biotechnology->subdomain:biotechnology:Bioprocessing Equipment", "source": "domain:biotechnology", "target": "subdomain:biotechnology:Bioprocessing Equipment", "edge_type": "HAS_SUBDOMAIN"}}, {"data": {"id": "subdomain:biotechnology:Bioprocessing Equipment->tech:Industrial Freeze Dryer (Lyophilizer)", "source": "subdomain:biotechnology:Bioprocessing Equipment", "target": "tech:Industrial Freeze Dryer (Lyophilizer)", "edge_type": "HAS_TECHNOLOGY"}}, {"data": {"id": "mat:Conformal coatings->domain:pharmaceuticals", "source": "mat:Conformal coatings", "target": "domain:pharmaceuticals", "edge_type": "USED_IN_DOMAIN"}}, {"data": {"id": "domain:pharmaceuticals->subdomain:pharmaceuticals:Clinical Trial Supply", "source": "domain:pharmaceuticals", "target": "subdomain:pharmaceuticals:Clinical Trial Supply", "edge_type": "HAS_SUBDOMAIN"}}, {"data": {"id": "subdomain:pharmaceuticals:Clinical Trial Supply->tech:Comparator Sourcing and Over-Encapsulation Machine", "source": "subdomain:pharmaceuticals:Clinical Trial Supply", "target": "tech:Comparator Sourcing and Over-Encapsulation Machine", "edge_type": "HAS_TECHNOLOGY"}}]}