{"country": "Mexico", "affected_technologies": [{"technology": "Smartphone", "num_materials_affected": 1, "num_components_affected": 1, "max_share_lost": 24.6, "top_producer_count": 1, "severity": "High", "materials": [{"material": "Silver", "share": 24.6, "is_top_producer": true}], "components": [{"component": "User Interface Module (Display and Keypad/Touchscreen)", "materials": [{"material": "Silver", "share": 24.6, "is_top_producer": true}]}]}, {"technology": "Electric Vehicle Battery", "num_materials_affected": 1, "num_components_affected": 1, "max_share_lost": 24.6, "top_producer_count": 1, "severity": "High", "materials": [{"material": "Silver", "share": 24.6, "is_top_producer": true}], "components": [{"component": "Power Distribution and Protection", "materials": [{"material": "Silver", "share": 24.6, "is_top_producer": true}]}]}, {"technology": "Superconducting Quantum Computer (Dilution Refrigerator-based)", "num_materials_affected": 1, "num_components_affected": 2, "max_share_lost": 24.6, "top_producer_count": 1, "severity": "High", "materials": [{"material": "Silver", "share": 24.6, "is_top_producer": true}], "components": [{"component": "Cooling Solution", "materials": [{"material": "Silver", "share": 24.6, "is_top_producer": true}]}, {"component": "Interconnects and Busbars", "materials": [{"material": "Silver", "share": 24.6, "is_top_producer": true}]}]}, {"technology": "Solar Panel", "num_materials_affected": 1, "num_components_affected": 1, "max_share_lost": 24.6, "top_producer_count": 1, "severity": "High", "materials": [{"material": "Silver", "share": 24.6, "is_top_producer": true}], "components": [{"component": "Monocrystalline Silicon Solar Cell", "materials": [{"material": "Silver", "share": 24.6, "is_top_producer": true}]}]}, {"technology": "RF Front-End Module (5G/4G)", "num_materials_affected": 1, "num_components_affected": 2, "max_share_lost": 24.6, "top_producer_count": 1, "severity": "High", "materials": [{"material": "Silver", "share": 24.6, "is_top_producer": true}], "components": [{"component": "Antenna Tuning and Matching Network", "materials": [{"material": "Silver", "share": 24.6, "is_top_producer": true}]}, {"component": "Duplexer / Multiplexer Module", "materials": [{"material": "Silver", "share": 24.6, "is_top_producer": true}]}]}, {"technology": "Capacitive Soil Moisture Sensor Probe (with MCU + radio)", "num_materials_affected": 1, "num_components_affected": 1, "max_share_lost": 24.6, "top_producer_count": 1, "severity": "High", "materials": [{"material": "Silver", "share": 24.6, "is_top_producer": true}], "components": [{"component": "Control System", "materials": [{"material": "Silver", "share": 24.6, "is_top_producer": true}]}]}], "summary": {"country": "Mexico", "total_technologies_affected": 6, "total_materials_affected": 1, "total_components_affected": 8, "critical_count": 0, "high_count": 6}}