{"country": "France", "affected_technologies": [{"technology": "Data Center Server", "num_materials_affected": 1, "num_components_affected": 1, "max_share_lost": 10.0, "top_producer_count": 0, "severity": "Moderate", "materials": [{"material": "Nitrogen", "share": 10.0, "is_top_producer": false, "dependency_type": "process_consumable"}], "components": [{"component": "", "materials": [{"material": "Nitrogen", "share": 10.0, "is_top_producer": false, "dependency_type": "process_consumable"}]}]}, {"technology": "Small Cell (5G Picocell)", "num_materials_affected": 1, "num_components_affected": 1, "max_share_lost": 8.0, "top_producer_count": 0, "severity": "Low", "materials": [{"material": "Nitrogen", "share": 8.0, "is_top_producer": false, "dependency_type": "process_consumable"}], "components": [{"component": "RF Transceiver Module", "materials": [{"material": "Nitrogen", "share": 8.0, "is_top_producer": false, "dependency_type": "process_consumable"}]}]}], "summary": {"country": "France", "total_technologies_affected": 2, "total_materials_affected": 1, "total_components_affected": 2, "critical_count": 0, "high_count": 0}}