{"nodes": [{"data": {"id": "mat:Argon", "label": "Argon", "layer": "material", "dependency_type": "constituent"}}, {"data": {"id": "domain:biotechnology", "label": "Biotechnology", "layer": "domain"}}, {"data": {"id": "subdomain:biotechnology:Agricultural Biotechnology", "label": "Agricultural Biotechnology", "layer": "subdomain"}}, {"data": {"id": "tech:Plant Transformation Gene Gun", "label": "Plant Transformation Gene Gun", "layer": "technology", "num_components": 1, "dependency_types": ["constituent"]}}, {"data": {"id": "subdomain:biotechnology:Biomedical Imaging", "label": "Biomedical Imaging", "layer": "subdomain"}}, {"data": {"id": "tech:Confocal Laser Scanning Microscope", "label": "Confocal Laser Scanning Microscope", "layer": "technology", "num_components": 1, "dependency_types": ["constituent"]}}, {"data": {"id": "tech:Cryo-Electron Microscope", "label": "Cryo-Electron Microscope", "layer": "technology", "num_components": 4, "dependency_types": ["constituent"]}}, {"data": {"id": "subdomain:biotechnology:Biopharmaceutical Production", "label": "Biopharmaceutical Production", "layer": "subdomain"}}, {"data": {"id": "tech:Continuous mRNA Manufacturing System", "label": "Continuous mRNA Manufacturing System", "layer": "technology", "num_components": 2, "dependency_types": ["constituent"]}}, {"data": {"id": "subdomain:biotechnology:Clinical Diagnostics", "label": "Clinical Diagnostics", "layer": "subdomain"}}, {"data": {"id": "tech:Automated Immunoassay Analyzer", "label": "Automated Immunoassay Analyzer", "layer": "technology", "num_components": 2, "dependency_types": ["constituent"]}}, {"data": {"id": "subdomain:biotechnology:Industrial Fermentation", "label": "Industrial Fermentation", "layer": "subdomain"}}, {"data": {"id": "tech:Industrial Enzyme Fermenter (50000L)", "label": "Industrial Enzyme Fermenter (50000L)", "layer": "technology", "num_components": 1, "dependency_types": ["constituent"]}}, {"data": {"id": "domain:microelectronics", "label": "Microelectronics", "layer": "domain"}}, {"data": {"id": "subdomain:microelectronics:Lighting and Photonics", "label": "Lighting and Photonics", "layer": "subdomain"}}, {"data": {"id": "tech:UV-C Disinfection System", "label": "UV-C Disinfection System", "layer": "technology", "num_components": 1, "dependency_types": ["constituent"]}}, {"data": {"id": "domain:pharmaceuticals", "label": "Pharmaceuticals", "layer": "domain"}}, {"data": {"id": "subdomain:pharmaceuticals:Continuous Manufacturing", "label": "Continuous Manufacturing", "layer": "subdomain"}}, {"data": {"id": "tech:Continuous Crystallization Unit", "label": "Continuous Crystallization Unit", "layer": "technology", "num_components": 1, "dependency_types": ["constituent"]}}, {"data": {"id": "subdomain:pharmaceuticals:Controlled Release Formulation", "label": "Controlled Release Formulation", "layer": "subdomain"}}, {"data": {"id": "tech:Wurster Column Coating Insert", "label": "Wurster Column Coating Insert", "layer": "technology", "num_components": 1, "dependency_types": ["constituent"]}}, {"data": {"id": "subdomain:pharmaceuticals:Pharmaceutical Water and Clean Utilities", "label": "Pharmaceutical Water and Clean Utilities", "layer": "subdomain"}}, {"data": {"id": "tech:TOC (Total Organic Carbon) Analyzer", "label": "TOC (Total Organic Carbon) Analyzer", "layer": "technology", "num_components": 1, "dependency_types": ["constituent"]}}, {"data": {"id": "subdomain:pharmaceuticals:Radiopharmaceutical Production", "label": "Radiopharmaceutical Production", "layer": "subdomain"}}, {"data": {"id": "tech:Radiochemical Dose Calibrator", "label": "Radiochemical Dose Calibrator", "layer": "technology", "num_components": 1, "dependency_types": ["constituent"]}}], "edges": [{"data": {"id": "mat:Argon->domain:biotechnology", "source": "mat:Argon", "target": "domain:biotechnology", "edge_type": "USED_IN_DOMAIN"}}, {"data": {"id": "domain:biotechnology->subdomain:biotechnology:Agricultural Biotechnology", "source": "domain:biotechnology", "target": "subdomain:biotechnology:Agricultural Biotechnology", "edge_type": "HAS_SUBDOMAIN"}}, {"data": {"id": "subdomain:biotechnology:Agricultural Biotechnology->tech:Plant Transformation Gene Gun", "source": "subdomain:biotechnology:Agricultural Biotechnology", "target": "tech:Plant Transformation Gene Gun", "edge_type": "HAS_TECHNOLOGY"}}, {"data": {"id": "domain:biotechnology->subdomain:biotechnology:Biomedical Imaging", "source": "domain:biotechnology", "target": "subdomain:biotechnology:Biomedical Imaging", "edge_type": "HAS_SUBDOMAIN"}}, {"data": {"id": "subdomain:biotechnology:Biomedical Imaging->tech:Confocal Laser Scanning Microscope", "source": "subdomain:biotechnology:Biomedical Imaging", "target": "tech:Confocal Laser Scanning Microscope", "edge_type": "HAS_TECHNOLOGY"}}, {"data": {"id": "subdomain:biotechnology:Biomedical Imaging->tech:Cryo-Electron Microscope", "source": "subdomain:biotechnology:Biomedical Imaging", "target": "tech:Cryo-Electron Microscope", "edge_type": "HAS_TECHNOLOGY"}}, {"data": {"id": "domain:biotechnology->subdomain:biotechnology:Biopharmaceutical Production", "source": "domain:biotechnology", "target": "subdomain:biotechnology:Biopharmaceutical Production", "edge_type": "HAS_SUBDOMAIN"}}, {"data": {"id": "subdomain:biotechnology:Biopharmaceutical Production->tech:Continuous mRNA Manufacturing System", "source": "subdomain:biotechnology:Biopharmaceutical Production", "target": "tech:Continuous mRNA Manufacturing System", "edge_type": "HAS_TECHNOLOGY"}}, {"data": {"id": "domain:biotechnology->subdomain:biotechnology:Clinical Diagnostics", "source": "domain:biotechnology", "target": "subdomain:biotechnology:Clinical Diagnostics", "edge_type": "HAS_SUBDOMAIN"}}, {"data": {"id": "subdomain:biotechnology:Clinical Diagnostics->tech:Automated Immunoassay Analyzer", "source": "subdomain:biotechnology:Clinical Diagnostics", "target": "tech:Automated Immunoassay Analyzer", "edge_type": "HAS_TECHNOLOGY"}}, {"data": {"id": "domain:biotechnology->subdomain:biotechnology:Industrial Fermentation", "source": "domain:biotechnology", "target": "subdomain:biotechnology:Industrial Fermentation", "edge_type": "HAS_SUBDOMAIN"}}, {"data": {"id": "subdomain:biotechnology:Industrial Fermentation->tech:Industrial Enzyme Fermenter (50000L)", "source": "subdomain:biotechnology:Industrial Fermentation", "target": "tech:Industrial Enzyme Fermenter (50000L)", "edge_type": "HAS_TECHNOLOGY"}}, {"data": {"id": "mat:Argon->domain:microelectronics", "source": "mat:Argon", "target": "domain:microelectronics", "edge_type": "USED_IN_DOMAIN"}}, {"data": {"id": "domain:microelectronics->subdomain:microelectronics:Lighting and Photonics", "source": "domain:microelectronics", "target": "subdomain:microelectronics:Lighting and Photonics", "edge_type": "HAS_SUBDOMAIN"}}, {"data": {"id": "subdomain:microelectronics:Lighting and Photonics->tech:UV-C Disinfection System", "source": "subdomain:microelectronics:Lighting and Photonics", "target": "tech:UV-C Disinfection System", "edge_type": "HAS_TECHNOLOGY"}}, {"data": {"id": "mat:Argon->domain:pharmaceuticals", "source": "mat:Argon", "target": "domain:pharmaceuticals", "edge_type": "USED_IN_DOMAIN"}}, {"data": {"id": "domain:pharmaceuticals->subdomain:pharmaceuticals:Continuous Manufacturing", "source": "domain:pharmaceuticals", "target": "subdomain:pharmaceuticals:Continuous Manufacturing", "edge_type": "HAS_SUBDOMAIN"}}, {"data": {"id": "subdomain:pharmaceuticals:Continuous Manufacturing->tech:Continuous Crystallization Unit", "source": "subdomain:pharmaceuticals:Continuous Manufacturing", "target": "tech:Continuous Crystallization Unit", "edge_type": "HAS_TECHNOLOGY"}}, {"data": {"id": "domain:pharmaceuticals->subdomain:pharmaceuticals:Controlled Release Formulation", "source": "domain:pharmaceuticals", "target": "subdomain:pharmaceuticals:Controlled Release Formulation", "edge_type": "HAS_SUBDOMAIN"}}, {"data": {"id": "subdomain:pharmaceuticals:Controlled Release Formulation->tech:Wurster Column Coating Insert", "source": "subdomain:pharmaceuticals:Controlled Release Formulation", "target": "tech:Wurster Column Coating Insert", "edge_type": "HAS_TECHNOLOGY"}}, {"data": {"id": "domain:pharmaceuticals->subdomain:pharmaceuticals:Pharmaceutical Water and Clean Utilities", "source": "domain:pharmaceuticals", "target": "subdomain:pharmaceuticals:Pharmaceutical Water and Clean Utilities", "edge_type": "HAS_SUBDOMAIN"}}, {"data": {"id": "subdomain:pharmaceuticals:Pharmaceutical Water and Clean Utilities->tech:TOC (Total Organic Carbon) Analyzer", "source": "subdomain:pharmaceuticals:Pharmaceutical Water and Clean Utilities", "target": "tech:TOC (Total Organic Carbon) Analyzer", "edge_type": "HAS_TECHNOLOGY"}}, {"data": {"id": "domain:pharmaceuticals->subdomain:pharmaceuticals:Radiopharmaceutical Production", "source": "domain:pharmaceuticals", "target": "subdomain:pharmaceuticals:Radiopharmaceutical Production", "edge_type": "HAS_SUBDOMAIN"}}, {"data": {"id": "subdomain:pharmaceuticals:Radiopharmaceutical Production->tech:Radiochemical Dose Calibrator", "source": "subdomain:pharmaceuticals:Radiopharmaceutical Production", "target": "tech:Radiochemical Dose Calibrator", "edge_type": "HAS_TECHNOLOGY"}}]}