{"country": "Madagascar", "affected_technologies": [{"technology": "Implantable Drug Infusion Pump", "num_materials_affected": 1, "num_components_affected": 1, "max_share_lost": 6.2, "top_producer_count": 0, "severity": "Low", "materials": [{"material": "Graphite", "share": 6.2, "is_top_producer": false, "dependency_type": "constituent"}], "components": [{"component": "Implantable Primary or Rechargeable Battery", "materials": [{"material": "Graphite", "share": 6.2, "is_top_producer": false, "dependency_type": "constituent"}]}]}, {"technology": "Continuous Glucose Monitor", "num_materials_affected": 1, "num_components_affected": 1, "max_share_lost": 6.2, "top_producer_count": 0, "severity": "Low", "materials": [{"material": "Graphite", "share": 6.2, "is_top_producer": false, "dependency_type": "constituent"}], "components": [{"component": "Battery or Power Source", "materials": [{"material": "Graphite", "share": 6.2, "is_top_producer": false, "dependency_type": "constituent"}]}]}, {"technology": "Portable Blood Coagulation Meter", "num_materials_affected": 1, "num_components_affected": 1, "max_share_lost": 6.2, "top_producer_count": 0, "severity": "Low", "materials": [{"material": "Graphite", "share": 6.2, "is_top_producer": false, "dependency_type": "constituent"}], "components": [{"component": "Battery Pack", "materials": [{"material": "Graphite", "share": 6.2, "is_top_producer": false, "dependency_type": "constituent"}]}]}, {"technology": "Handheld Pulse Oximeter", "num_materials_affected": 1, "num_components_affected": 1, "max_share_lost": 6.2, "top_producer_count": 0, "severity": "Low", "materials": [{"material": "Graphite", "share": 6.2, "is_top_producer": false, "dependency_type": "constituent"}], "components": [{"component": "Rechargeable Lithium-ion or Alkaline Battery Pack", "materials": [{"material": "Graphite", "share": 6.2, "is_top_producer": false, "dependency_type": "constituent"}]}]}], "summary": {"country": "Madagascar", "total_technologies_affected": 4, "total_materials_affected": 1, "total_components_affected": 4, "critical_count": 0, "high_count": 0}}