{"country": "Malaysia", "affected_technologies": [{"technology": "Inertial Navigation System", "num_materials_affected": 1, "num_components_affected": 1, "max_share_lost": 60.0, "top_producer_count": 1, "severity": "Critical", "materials": [{"material": "Nitrile or latex gloves", "share": 60.0, "is_top_producer": true, "dependency_type": "process_consumable"}], "components": [{"component": "", "materials": [{"material": "Nitrile or latex gloves", "share": 60.0, "is_top_producer": true, "dependency_type": "process_consumable"}]}]}], "summary": {"country": "Malaysia", "total_technologies_affected": 1, "total_materials_affected": 1, "total_components_affected": 1, "critical_count": 1, "high_count": 0}}