{"nodes": [{"data": {"id": "mat:Epoxy resins", "label": "Epoxy resins", "layer": "material", "dependency_type": "constituent"}}, {"data": {"id": "domain:biotechnology", "label": "Biotechnology", "layer": "domain"}}, {"data": {"id": "subdomain:biotechnology:Agricultural Biotechnology", "label": "Agricultural Biotechnology", "layer": "subdomain"}}, {"data": {"id": "tech:Biopesticide Fermentation Unit", "label": "Biopesticide Fermentation Unit", "layer": "technology", "num_components": 1, "dependency_types": ["process_consumable"]}}, {"data": {"id": "domain:microelectronics", "label": "Microelectronics", "layer": "domain"}}, {"data": {"id": "subdomain:microelectronics:Robotics and Motion", "label": "Robotics and Motion", "layer": "subdomain"}}, {"data": {"id": "tech:Collaborative Robot (Cobot) Arm", "label": "Collaborative Robot (Cobot) Arm", "layer": "technology", "num_components": 1, "dependency_types": ["constituent"]}}], "edges": [{"data": {"id": "mat:Epoxy resins->domain:biotechnology", "source": "mat:Epoxy resins", "target": "domain:biotechnology", "edge_type": "USED_IN_DOMAIN"}}, {"data": {"id": "domain:biotechnology->subdomain:biotechnology:Agricultural Biotechnology", "source": "domain:biotechnology", "target": "subdomain:biotechnology:Agricultural Biotechnology", "edge_type": "HAS_SUBDOMAIN"}}, {"data": {"id": "subdomain:biotechnology:Agricultural Biotechnology->tech:Biopesticide Fermentation Unit", "source": "subdomain:biotechnology:Agricultural Biotechnology", "target": "tech:Biopesticide Fermentation Unit", "edge_type": "HAS_TECHNOLOGY"}}, {"data": {"id": "mat:Epoxy resins->domain:microelectronics", "source": "mat:Epoxy resins", "target": "domain:microelectronics", "edge_type": "USED_IN_DOMAIN"}}, {"data": {"id": "domain:microelectronics->subdomain:microelectronics:Robotics and Motion", "source": "domain:microelectronics", "target": "subdomain:microelectronics:Robotics and Motion", "edge_type": "HAS_SUBDOMAIN"}}, {"data": {"id": "subdomain:microelectronics:Robotics and Motion->tech:Collaborative Robot (Cobot) Arm", "source": "subdomain:microelectronics:Robotics and Motion", "target": "tech:Collaborative Robot (Cobot) Arm", "edge_type": "HAS_TECHNOLOGY"}}]}